k8stools/__init__.py
k8stools/k8s_tools.py
k8stools/mcp_client.py
k8stools/mcp_server.py
k8stools/mock_tools.py
k8stools-1.0.1.dist-info/METADATA
k8stools-1.0.1.dist-info/WHEEL
k8stools-1.0.1.dist-info/entry_points.txt
k8stools-1.0.1.dist-info/licenses/LICENSE
k8stools-1.0.1.dist-info/RECORD
