Metadata-Version: 2.4
Name: k8stools
Version: 1.0.1
Summary: Tools and an MCP server for building Kubernetes agents
Project-URL: Homepage, https://github.com/BenedatLLC/k8stools
Author: Jeff Fischer
License:                                  Apache License
License-File: LICENSE
Classifier: License :: OSI Approved :: Apache Software License
Classifier: Operating System :: OS Independent
Classifier: Programming Language :: Python :: 3
Requires-Python: >=3.12
Requires-Dist: kubernetes>=33.1.0
Requires-Dist: mcp>=1.12.0
